LICENSE
README.rst
deepwordle/__init__.py
deepwordle/app.py
deepwordle/audio_record.py
deepwordle/components/__init__.py
deepwordle/components/constants.py
deepwordle/components/data/wordle-answers.txt
deepwordle/components/data/wordle-guesses.txt
deepwordle/components/letter.py
deepwordle/components/letters_grid.py
deepwordle/components/message.py
deepwordle/components/rich_text.py
deepwordle/components/utils.py
deepwordle/transcribe.py
deepwordle/twitter.py
deepwordle-0.1.0.dist-info/entry_points.txt
deepwordle-0.1.0.dist-info/LICENSE
deepwordle-0.1.0.dist-info/WHEEL
deepwordle-0.1.0.dist-info/METADATA
deepwordle-0.1.0.dist-info/RECORD
