Metadata-Version: 2.1
Name: deepwordle
Version: 0.1.0
Summary: deepwordle is a wordle clone game powered by deepgram, textual, tweepy, and friends.
Home-page: https://github.com/Harmouch101/deepwordle
License: MIT
Keywords: python,frozendict,deepwordle
Author: Harmouch101
Author-email: eng.mahmoudharmouch@gmail.com
Requires-Python: >=3.10,<4.0
Classifier: Development Status :: 2 - Pre-Alpha
Classifier: Intended Audience :: Developers
Classifier: License :: OSI Approved :: MIT License
Classifier: Natural Language :: English
Classifier: Programming Language :: Python :: 3
Classifier: Programming Language :: Python :: 3.10
Classifier: Programming Language :: Python :: 3.8
Classifier: Programming Language :: Python :: 3.9
Requires-Dist: PyAudio (>=0.2.11,<0.3.0)
Requires-Dist: deepgram-sdk (>=0.2.5,<0.3.0)
Requires-Dist: nest-asyncio (>=1.5.5,<2.0.0)
Requires-Dist: pyfiglet (>=0.8.post1,<0.9)
Requires-Dist: rich (>=12.2.0,<13.0.0)
Requires-Dist: textual (>=0.1.17,<0.2.0)
Requires-Dist: tweepy (>=4.8.0,<5.0.0)
Project-URL: Repository, https://github.com/Harmouch101/deepwordle
